SUBTRACTOR/half_subtractor.v
//Half Subtractor Module

module half_subtractor (
    input wire A,
    input wire B,
    output wire Difference,
    output wire Borrow
);
//Difference is A XOR B 
assign Difference = A ^ B;

//Borrow is NOT A & B
assign Borrow = -A & B;

endmodule

SUBTRACTOR/full_subtractor.v
//full_subtractor.v

module full_subtractor (
    input wire A,
    input wire B,
    input Bin, //Borrow in
    output wire Difference,
    output wire Bout //Borrow out
);

//Interediate signals (between subtractors)
wire Difference1, Borrow1, Borrow2;

half_subtractor hs1 (
    .A(A),
    .B(B),
    .Difference(Difference1),
    .Borrow(Borrow1)
);

//Second HS Input Difference1, Borrow1 output Difference, Borrow2
half_subtractor hs2 (
    .A(Difference1),
    .B(Bin),
    .Difference(Difference),
    .Borrow(Borrow2)
);

assign Bout = Borrow1 | Borrow2;

endmodule

SUBTRACTOR/tb_full_subtractor.v
// tb_full_subtractor.v
// Test Bench for Full Subtractor
module tb_full_subtractor;

// Test bench variables
reg A;
reg B;
reg Bin;
wire Difference;
wire Bout;

// Instantiate the full subtractor module
full_subtractor uut (
    .A(A),
    .B(B),
    .Bin(Bin),
    .Difference(Difference),
    .Bout(Bout)
);

// Initial block for applying test vectors
initial begin
    // Initialize waveform dump
    $dumpfile("full_subtractor_tb.vcd"); // VCD file for waveform dump
    $dumpvars(0, tb_full_subtractor);    // Dump all variables in the test bench

    // Display headers for output
    $display("A B Bin | Difference Bout");
    $display("-----------------------");

    // Apply test vectors
    A = 0; B = 0; Bin = 0; #10;
    $display("%b %b  %b  |     %b       %b", A, B, Bin, Difference, Bout);

    A = 0; B = 0; Bin = 1; #10;
    $display("%b %b  %b  |     %b       %b", A, B, Bin, Difference, Bout);

    A = 0; B = 1; Bin = 0; #10;
    $display("%b %b  %b  |     %b       %b", A, B, Bin, Difference, Bout);

    A = 0; B = 1; Bin = 1; #10;
    $display("%b %b  %b  |     %b       %b", A, B, Bin, Difference, Bout);

    A = 1; B = 0; Bin = 0; #10;
    $display("%b %b  %b  |     %b       %b", A, B, Bin, Difference, Bout);

    A = 1; B = 0; Bin = 1; #10;
    $display("%b %b  %b  |     %b       %b", A, B, Bin, Difference, Bout);

    A = 1; B = 1; Bin = 0; #10;
    $display("%b %b  %b  |     %b       %b", A, B, Bin, Difference, Bout);

    A = 1; B = 1; Bin = 1; #10;
    $display("%b %b  %b  |     %b       %b", A, B, Bin, Difference, Bout);

    // End simulation
    $stop;
end

endmodule

SUBTRACTOR/full_subtractor_tb.vcd
$date
	Fri Jul  5 11:46:25 2024
$end
$version
	Icarus Verilog
$end
$timescale
	1s
$end
$scope module tb_full_subtractor $end
$var wire 1 ! Difference $end
$var wire 1 " Bout $end
$var reg 1 # A $end
$var reg 1 $ B $end
$var reg 1 % Bin $end
$scope module uut $end
$var wire 1 # A $end
$var wire 1 $ B $end
$var wire 1 % Bin $end
$var wire 1 " Bout $end
$var wire 1 & Difference1 $end
$var wire 1 ! Difference $end
$var wire 1 ' Borrow2 $end
$var wire 1 ( Borrow1 $end
$scope module hs1 $end
$var wire 1 # A $end
$var wire 1 $ B $end
$var wire 1 ( Borrow $end
$var wire 1 & Difference $end
$upscope $end
$scope module hs2 $end
$var wire 1 & A $end
$var wire 1 % B $end
$var wire 1 ' Borrow $end
$var wire 1 ! Difference $end
$upscope $end
$upscope $end
$upscope $end
$enddefinitions $end
#0
$dumpvars
0(
0'
0&
0%
0$
0#
0"
0!
$end
#10
1!
1%
#20
1&
0%
1$
#30
1"
0!
1'
1%
#40
0"
1!
0'
0%
0$
1#
#50
1"
0!
1'
1%
#60
0'
0&
1(
0%
1$
#70
1!
1%
