ADDER/half_adder.v
//Module for Half Adder
module half_adder (
    input wire A,   //Input bit A
    input wire B,   //Input bit B
    output wire Sum,    //output sum
    output wire Carry //output carry
);

//Sum is A XOR B
assign Sum = A ^ B;
assign Carry = A & B; 

endmodule

ADDER/full_adder.v
//full_adder.v
//Full Adder Module

//Two half adders and OR gate

//Inputs A,B,Cin Outputs Sum,Cout
module full_adder (
    input wire A,
    input wire B,
    input wire Cin,
    output wire Sum,
    output wire Cout
);

//Intermediate signals (between half adders)
wire Sum1, Carry1, Carry2;

//First HA Input A,B Output Sum1,Carry1
half_adder ha1 (
    .A(A),
    .B(B),
    .Sum(Sum1),
    .Carry(Carry1)
);

//Second HA Input Sum1, Cin Output Sum, Carry2
half_adder ha2 (
        .A(Sum1),
        .B(Cin),
        .Sum(Sum),
        .Carry(Carry2)
);

//OR gate for potential carry from Carry1,Carry2
assign Cout = Carry1 | Carry2;


endmodule

ADDER/tb_full_adder.v
//tb_full_adder.v
//Test Bench for Full Adder

module tb_full_adder;

//Create Bench variables
reg A;
reg B;
reg Cin;
wire Sum;
wire Cout;

full_adder uut (
    .A(A),
    .B(B),
    .Cin(Cin),
    .Sum(Sum),
    .Cout(Cout)
);

//Initial block for test vectors
initial begin  
  //dump waveform data
  $dumpfile("full_adder_tb.vcd");
  $dumpvars(0, tb_full_adder);
  // Display headers for output
    $display("A B Cin | Sum Cout");
    $display("-----------------");

    // Apply test vectors
    A = 0; B = 0; Cin = 0; #10;
    $display("%b %b  %b  |  %b   %b", A, B, Cin, Sum, Cout);

    A = 0; B = 0; Cin = 1; #10;
    $display("%b %b  %b  |  %b   %b", A, B, Cin, Sum, Cout);

    A = 0; B = 1; Cin = 0; #10;
    $display("%b %b  %b  |  %b   %b", A, B, Cin, Sum, Cout);

    A = 0; B = 1; Cin = 1; #10;
    $display("%b %b  %b  |  %b   %b", A, B, Cin, Sum, Cout);

    A = 1; B = 0; Cin = 0; #10;
    $display("%b %b  %b  |  %b   %b", A, B, Cin, Sum, Cout);

    A = 1; B = 0; Cin = 1; #10;
    $display("%b %b  %b  |  %b   %b", A, B, Cin, Sum, Cout);

    A = 1; B = 1; Cin = 0; #10;
    $display("%b %b  %b  |  %b   %b", A, B, Cin, Sum, Cout);

    A = 1; B = 1; Cin = 1; #10;
    $display("%b %b  %b  |  %b   %b", A, B, Cin, Sum, Cout);

    // End simulation
    $stop;
end

endmodule

ADDER/full_adder_tb.vcd
$date
	Thu Jul  4 10:38:53 2024
$end
$version
	Icarus Verilog
$end
$timescale
	1s
$end
$scope module tb_full_adder $end
$var wire 1 ! Sum $end
$var wire 1 " Cout $end
$var reg 1 # A $end
$var reg 1 $ B $end
$var reg 1 % Cin $end
$scope module uut $end
$var wire 1 # A $end
$var wire 1 $ B $end
$var wire 1 % Cin $end
$var wire 1 " Cout $end
$var wire 1 & Sum1 $end
$var wire 1 ! Sum $end
$var wire 1 ' Carry2 $end
$var wire 1 ( Carry1 $end
$scope module ha1 $end
$var wire 1 # A $end
$var wire 1 $ B $end
$var wire 1 ( Carry $end
$var wire 1 & Sum $end
$upscope $end
$scope module ha2 $end
$var wire 1 & A $end
$var wire 1 % B $end
$var wire 1 ' Carry $end
$var wire 1 ! Sum $end
$upscope $end
$upscope $end
$upscope $end
$enddefinitions $end
#0
$dumpvars
0(
0'
0&
0%
0$
0#
0"
0!
$end
#10
1!
1%
#20
1&
0%
1$
#30
1"
0!
1'
1%
#40
0"
1!
0'
0%
0$
1#
#50
1"
0!
1'
1%
#60
0'
0&
1(
0%
1$
#70
1!
1%
